theodore/OB_repl.py
theodore/Om_descriptors.py
theodore/__init__.py
theodore/atominfo.py
theodore/cclib_interface.py
theodore/dens_ana_base.py
theodore/error_handler.py
theodore/fchk_parser.py
theodore/file_parser.py
theodore/input_options.py
theodore/lib_NICS.py
theodore/lib_diab.py
theodore/lib_exciton.py
theodore/lib_file.py
theodore/lib_mo.py
theodore/lib_plot.py
theodore/lib_pytest.py
theodore/lib_sden.py
theodore/lib_soc.py
theodore/lib_struc.py
theodore/lib_tden.py
theodore/lib_util.py
theodore/orbkit_full.py
theodore/orbkit_interface.py
theodore/pop_ana.py
theodore/theo_header.py
theodore/units.py
theodore/actions/__init__.py
theodore/actions/actions.py
theodore/actions/analyze_NOs.py
theodore/actions/analyze_correlations.py
theodore/actions/analyze_sden.py
theodore/actions/analyze_tden.py
theodore/actions/plot_vist.py
theodore/actions/theoinp.py
theodore/actions/theotools.py
theodore/scripts/__init__.py
theodore/scripts/a.py
theodore/scripts/analyze_NOs.py
theodore/scripts/analyze_correlations.py
theodore/scripts/analyze_sden.py
theodore/scripts/analyze_tden.py
theodore/scripts/analyze_tden_soc.py
theodore/scripts/analyze_tden_unr.py
theodore/scripts/babel.py
theodore/scripts/cc2molden.py
theodore/scripts/cc_check.py
theodore/scripts/cc_opt.py
theodore/scripts/convert_table.py
theodore/scripts/dgrid_prep.py
theodore/scripts/draw_moments.py
theodore/scripts/ex.py
theodore/scripts/extract_molden.py
theodore/scripts/fcd.py
theodore/scripts/jmol_MOs.py
theodore/scripts/jmol_vibs.py
theodore/scripts/parse_libwfa.py
theodore/scripts/plot_OmFrag.py
theodore/scripts/plot_Om_bars.py
theodore/scripts/plot_VIST.py
theodore/scripts/plot_frag_decomp.py
theodore/scripts/plot_graph.py
theodore/scripts/plot_graph_nx.py
theodore/scripts/spectrum.py
theodore/scripts/tden_OV.py
theodore/scripts/theoinp.py
theodore/scripts/theotools.py
theodore/scripts/vmd_plots.py
theodore-2.5.0.dist-info/LICENSE.txt
theodore-2.5.0.dist-info/METADATA
theodore-2.5.0.dist-info/WHEEL
theodore-2.5.0.dist-info/entry_points.txt
theodore-2.5.0.dist-info/top_level.txt
theodore-2.5.0.dist-info/RECORD
