Metadata-Version: 2.1
Name: theodore
Version: 2.5.0
Summary: Theoretical Density, Orbital Relaxation and Exciton analysis
Home-page: https://github.com/felixplasser/theodore-qc
Author: Felix Plasser
License: GNU General Public License 3.0
Keywords: theodore
Platform: UNKNOWN
Classifier: Development Status :: 2 - Pre-Alpha
Classifier: Intended Audience :: Developers
Classifier: License :: OSI Approved :: GNU General Public License v3 (GPLv3)
Classifier: Natural Language :: English
Classifier: Programming Language :: Python :: 3.6
Classifier: Programming Language :: Python :: 3.7
Classifier: Programming Language :: Python :: 3.8
Classifier: Programming Language :: Python :: 3.9
Requires-Python: >=3.6, !=3.0.*, !=3.1.*, !=3.2.*, !=3.3.*, !=3.4.*, !=3.5*
Requires-Dist: pycolt (>=0.5)
Requires-Dist: cclib (>=1.7)
Requires-Dist: numpy (>=1.17)
